iconbuilder
