Metadata-Version: 1.0
Name: iconbuilder
Version: 0.0.2
Summary: just a simple image resizer
Home-page: https://github.com/stevefermi/IconBuilder
Author: Xiaozhe Yaoi@zhitan
Author-email: xiaozhe.yaoi@gmail.com
License: GPL License
Keywords: image,resizer
Platform: any
